{"errors":[],"warnings":[],"namedChunkGroups":{"app":{"chunks":[4,2,3,0],"assets":["webpack-runtime-0a4c9a9e77c04d56979c.js","webpack-runtime-0a4c9a9e77c04d56979c.js.map","framework-dd824ea10d83e3e5a212.js","framework-dd824ea10d83e3e5a212.js.map","styles.4a67c2d5e37df47f3b0e.css","styles-dd3841a4888192e20843.js","styles-dd3841a4888192e20843.js.map","app-4447fbb728774816cbf1.js","app-4447fbb728774816cbf1.js.map"],"children":{},"childAssets":{}},"component---src-pages-index-js":{"chunks":[1],"assets":["component---src-pages-index-js-6449a45c09312cb09691.js","component---src-pages-index-js-6449a45c09312cb09691.js.map"],"children":{},"childAssets":{}}},"assetsByChunkName":{"app":["webpack-runtime-0a4c9a9e77c04d56979c.js","framework-dd824ea10d83e3e5a212.js","styles.4a67c2d5e37df47f3b0e.css","styles-dd3841a4888192e20843.js","app-4447fbb728774816cbf1.js"],"component---src-pages-index-js":["component---src-pages-index-js-6449a45c09312cb09691.js"]}}